karrio/server/iam/__init__.py
karrio/server/iam/admin.py
karrio/server/iam/apps.py
karrio/server/iam/models.py
karrio/server/iam/permissions.py
karrio/server/iam/serializers.py
karrio/server/iam/signals.py
karrio/server/iam/tests.py
karrio/server/iam/views.py
karrio/server/iam/migrations/0001_initial.py
karrio/server/iam/migrations/__init__.py
karrio/server/settings/iam.py
karrio.server.iam-2023.1.dist-info/METADATA
karrio.server.iam-2023.1.dist-info/WHEEL
karrio.server.iam-2023.1.dist-info/top_level.txt
karrio.server.iam-2023.1.dist-info/RECORD
