Metadata-Version: 2.1
Name: karrio.server.iam
Version: 2023.1
Summary: Multi-carrier shipping API iam module
Home-page: https://github.com/karrioapi/karrio
Author: karrio
Author-email: hello@karrio.io
License: Apache-2.0
Classifier: Programming Language :: Python :: 3
Requires-Dist: karrio.server.core
